vf.py
vf-0.0.2.dist-info/LICENSE.txt
vf-0.0.2.dist-info/WHEEL
vf-0.0.2.dist-info/METADATA
vf-0.0.2.dist-info/RECORD
