Metadata-Version: 2.1
Name: vf
Version: 0.0.2
Summary: VF: Validation Functions (for Python dicts.)
Home-page: https://github.com/polydojo/vf
License: UNKNOWN
Author: Polydojo, Inc.
Author-email: 8079593+sumukhbarve@users.noreply.github.com
Classifier: License :: OSI Approved :: MIT License
